image_to_psd/__init__.py
image_to_psd/color_printer.py
image_to_psd/processor.py
tests/__init__.py
tests/test_color_printer.py
tests/test_processor.py
image_to_psd-1.1.0.dist-info/LICENSE
image_to_psd-1.1.0.dist-info/METADATA
image_to_psd-1.1.0.dist-info/WHEEL
image_to_psd-1.1.0.dist-info/top_level.txt
image_to_psd-1.1.0.dist-info/RECORD
